Metadata-Version: 2.1
Name: bkv
Version: 0.0.2
Summary: A simple kv store
Home-page: https://github.com/xupingmao/bkv
Author: mark
Author-email: 578749341@qq.com
Classifier: Programming Language :: Python :: 3
Classifier: License :: OSI Approved :: MIT License
Classifier: Operating System :: OS Independent
